Metadata-Version: 2.1
Name: odoo10-addon-l10n-es-vat-book-oss
Version: 10.0.1.0.0.99.dev3
Summary: Libro de IVA OSS
Home-page: https://github.com/OCA/l10n-spain
Author: Sygel, Odoo Community Association (OCA)
Author-email: support@odoo-community.org
License: AGPL-3
Platform: UNKNOWN
Classifier: Programming Language :: Python
Classifier: Framework :: Odoo
Classifier: Framework :: Odoo :: 10.0
Classifier: License :: OSI Approved :: GNU Affero General Public License v3
Classifier: Development Status :: 4 - Beta
Requires-Python: ~=2.7
Requires-Dist: odoo10-addon-l10n-es-vat-book
Requires-Dist: odoo10-addon-l10n-eu-oss
Requires-Dist: odoo <10.1dev,>=10.0
